bootstrap4/__init__.py
bootstrap4/__pycache__/__init__.cpython-36.pyc
bootstrap4/__pycache__/__init__.cpython-37.pyc
bootstrap4/__pycache__/__init__.cpython-39.pyc
bootstrap4/static/css/bootstrap-grid.css
bootstrap4/static/css/bootstrap-grid.css.map
bootstrap4/static/css/bootstrap-grid.min.css
bootstrap4/static/css/bootstrap-grid.min.css.map
bootstrap4/static/css/bootstrap-reboot.css
bootstrap4/static/css/bootstrap-reboot.css.map
bootstrap4/static/css/bootstrap-reboot.min.css
bootstrap4/static/css/bootstrap-reboot.min.css.map
bootstrap4/static/css/bootstrap.css
bootstrap4/static/css/bootstrap.css.map
bootstrap4/static/css/bootstrap.min.css
bootstrap4/static/css/bootstrap.min.css.map
bootstrap4/static/js/bootstrap.bundle.js
bootstrap4/static/js/bootstrap.bundle.js.map
bootstrap4/static/js/bootstrap.bundle.min.js
bootstrap4/static/js/bootstrap.bundle.min.js.map
bootstrap4/static/js/bootstrap.js
bootstrap4/static/js/bootstrap.js.map
bootstrap4/static/js/bootstrap.min.js
bootstrap4/static/js/bootstrap.min.js.map
bootstrap4/static/js/jquery-3.6.0.slim.min.js
bootstrap4/static/js/popper.min.js
bootstrap4/static/js/popper.min.js.map
bootstrap4/templates/base.html
bootstrap4/templates/messages.inc.html
minimal_django_bootstrap4-0.2.3.dist-info/METADATA
minimal_django_bootstrap4-0.2.3.dist-info/WHEEL
minimal_django_bootstrap4-0.2.3.dist-info/top_level.txt
minimal_django_bootstrap4-0.2.3.dist-info/RECORD
