Metadata-Version: 2.1
Name: minimal-django-bootstrap4
Version: 0.2.3
Home-page: http://github.com/kfdm/django-bootstrap4
Author: Paul Traylor
License: MIT License
Project-URL: Issues, http://github.com/kfdm/django-bootstrap4/issues
Project-URL: Source Code, http://github.com/kfdm/django-bootstrap4
Keywords: django
Classifier: Environment :: Web Environment
Classifier: Framework :: Django
Classifier: Intended Audience :: Developers
Classifier: License :: OSI Approved :: MIT License
Classifier: Operating System :: OS Independent
Classifier: Programming Language :: Python
Classifier: Programming Language :: Python :: 3
Classifier: Programming Language :: Python :: 3 :: Only
Classifier: Programming Language :: Python :: 3.6
Classifier: Programming Language :: Python :: 3.7
Classifier: Programming Language :: Python :: 3.8
Classifier: Programming Language :: Python :: 3.9
Classifier: Programming Language :: Python :: 3.10
Classifier: Topic :: Internet :: WWW/HTTP
Classifier: Topic :: Internet :: WWW/HTTP :: Dynamic Content
Requires-Python: >=3.6
Requires-Dist: Django (>=2.0)
Requires-Dist: importlib-metadata (>=1.0) ; python_version < "3.8"
